{"kind": "youtube#videoListResponse", "etag": "\"j6xRRd8dTPVVptg711_CSPADRfg/HFqQruGPFGXEh79h5XiFc9yNljg\"", "pageInfo": {"totalResults": 26, "resultsPerPage": 26}, "items": [{"kind": "youtube#video", "etag": "\"j6xRRd8dTPVVptg711_CSPADRfg/RnXK2H817eWFyIdmJtKpl4lVmC0\"", "id": "eEsahu-1SEw", "contentDetails": {"duration": "PT11M38S", "dimension": "2d", "definition": "hd", "caption": "false", "licensedContent": true, "projection": "rectangular"}}, {"kind": "youtube#video", "etag": "\"j6xRRd8dTPVVptg711_CSPADRfg/KQRiQjQGDdc_tXqjgxO-Ifx5jHc\"", "id": "76l6kEb4BQA", "contentDetails": {"duration": "PT16M32S", "dimension": "2d", "definition": "hd", "caption": "false", "licensedContent": true, "projection": "rectangular"}}, {"kind": "youtube#video", "etag": "\"j6xRRd8dTPVVptg711_CSPADRfg/cncUVCPKj1qPC9VUn0aezp4sKho\"", "id": "7UPxQAvb6E0", "contentDetails": {"duration": "PT1H12M32S", "dimension": "2d", "definition": "hd", "caption": "false", "licensedContent": false, "projection": "rectangular"}}, {"kind": "youtube#video", "etag": "\"j6xRRd8dTPVVptg711_CSPADRfg/1oOcMcWAPg57e22fyB_ELXuI05Q\"", "id": "92qBV985uXY", "contentDetails": {"duration": "PT37M37S", "dimension": "2d", "definition": "hd", "caption": "false", "licensedContent": false, "projection": "rectangular"}}, {"kind": "youtube#video", "etag": "\"j6xRRd8dTPVVptg711_CSPADRfg/QFGqcTIEijvNpNjEVvg6q-BMDxA\"", "id": "7bW-ewETvvU", "contentDetails": {"duration": "PT8M19S", "dimension": "2d", "definition": "sd", "caption": "false", "licensedContent": false, "projection": "rectangular"}}, {"kind": "youtube#video", "etag": "\"j6xRRd8dTPVVptg711_CSPADRfg/c8O1b0lQQbDHlXqMgVl-M4z779U\"", "id": "MIwDUVo6VNc", "contentDetails": {"duration": "PT6M3S", "dimension": "2d", "definition": "hd", "caption": "false", "licensedContent": true, "projection": "rectangular"}}, {"kind": "youtube#video", "etag": "\"j6xRRd8dTPVVptg711_CSPADRfg/ekW1sL7zqBbHvj6QkgGtREdGUTA\"", "id": "SL3afJqXU50", "contentDetails": {"duration": "PT5M27S", "dimension": "2d", "definition": "hd", "caption": "false", "licensedContent": true, "projection": "rectangular"}}, {"kind": "youtube#video", "etag": "\"j6xRRd8dTPVVptg711_CSPADRfg/XOoPX2M4sWJN28-yWujgLyUgYms\"", "id": "eEoAYuOtA-w", "contentDetails": {"duration": "PT2M32S", "dimension": "2d", "definition": "hd", "caption": "false", "licensedContent": false, "projection": "rectangular"}}, {"kind": "youtube#video", "etag": "\"j6xRRd8dTPVVptg711_CSPADRfg/NgxjyEKajTj4P1nxoUw1mRjcR3w\"", "id": "BObriZ_-6NY", "contentDetails": {"duration": "PT54M47S", "dimension": "2d", "definition": "hd", "caption": "false", "licensedContent": true, "regionRestriction": {"blocked": ["TR"]}, "projection": "rectangular"}}, {"kind": "youtube#video", "etag": "\"j6xRRd8dTPVVptg711_CSPADRfg/eOAz4W6m9YOZZhg2YUDie9JBOy8\"", "id": "uPc2Zwus3Rc", "contentDetails": {"duration": "PT6M36S", "dimension": "2d", "definition": "hd", "caption": "true", "licensedContent": true, "contentRating": {"ytRating": "ytAgeRestricted"}, "projection": "rectangular"}}, {"kind": "youtube#video", "etag": "\"j6xRRd8dTPVVptg711_CSPADRfg/9j7QLd3U__CSIf3PR_6o7_EwFn8\"", "id": "xrKrdOUKUDo", "contentDetails": {"duration": "PT29M52S", "dimension": "2d", "definition": "hd", "caption": "false", "licensedContent": false, "projection": "rectangular"}}, {"kind": "youtube#video", "etag": "\"j6xRRd8dTPVVptg711_CSPADRfg/GMVEUnaa0PdrQINEjoQ0KUjYxxo\"", "id": "EAlQc84D9lU", "contentDetails": {"duration": "PT3M33S", "dimension": "2d", "definition": "hd", "caption": "true", "licensedContent": true, "projection": "rectangular"}}, {"kind": "youtube#video", "etag": "\"j6xRRd8dTPVVptg711_CSPADRfg/QgjXGXG3vloc9yx0vZgNtU2Wo5I\"", "id": "JjwYl8yXwuQ", "contentDetails": {"duration": "PT8M52S", "dimension": "2d", "definition": "hd", "caption": "false", "licensedContent": true, "projection": "rectangular"}}, {"kind": "youtube#video", "etag": "\"j6xRRd8dTPVVptg711_CSPADRfg/LWducFR2OB_LdVk4_tCAqceMsXI\"", "id": "v1f7oa_uyTw", "contentDetails": {"duration": "PT8M3S", "dimension": "2d", "definition": "hd", "caption": "false", "licensedContent": false, "projection": "rectangular"}}, {"kind": "youtube#video", "etag": "\"j6xRRd8dTPVVptg711_CSPADRfg/uRZC5fHGyvPBdb0y_ioZbL_nnYE\"", "id": "jvNefGT0qQY", "contentDetails": {"duration": "PT3M1S", "dimension": "2d", "definition": "hd", "caption": "true", "licensedContent": true, "projection": "rectangular"}}, {"kind": "youtube#video", "etag": "\"j6xRRd8dTPVVptg711_CSPADRfg/mvSwD45yHgCkGnadCGORtiScrbE\"", "id": "-n__GSNwHGc", "contentDetails": {"duration": "PT2M51S", "dimension": "2d", "definition": "hd", "caption": "false", "licensedContent": false, "projection": "rectangular"}}, {"kind": "youtube#video", "etag": "\"j6xRRd8dTPVVptg711_CSPADRfg/lxbR8uoBPyMTc2srTyFG6gUmhLU\"", "id": "sWy8L1f-BmM", "contentDetails": {"duration": "PT1M36S", "dimension": "2d", "definition": "hd", "caption": "false", "licensedContent": true, "projection": "rectangular"}}, {"kind": "youtube#video", "etag": "\"j6xRRd8dTPVVptg711_CSPADRfg/YrL2kb65RjMBsuLhjpdYDi_v02c\"", "id": "ZAyvEft9MIs", "contentDetails": {"duration": "PT21M58S", "dimension": "2d", "definition": "hd", "caption": "true", "licensedContent": true, "projection": "rectangular"}}, {"kind": "youtube#video", "etag": "\"j6xRRd8dTPVVptg711_CSPADRfg/9LFlvio2_Tu9BhJ5jsy7F2wE6MI\"", "id": "bfmX4NJpi4g", "contentDetails": {"duration": "PT2M50S", "dimension": "2d", "definition": "hd", "caption": "false", "licensedContent": true, "projection": "rectangular"}}, {"kind": "youtube#video", "etag": "\"j6xRRd8dTPVVptg711_CSPADRfg/bVk6ayqg9UrNygqsMpq1Z3yiEMI\"", "id": "IjLdwhY6fyg", "contentDetails": {"duration": "PT11M43S", "dimension": "2d", "definition": "hd", "caption": "false", "licensedContent": true, "projection": "rectangular"}}, {"kind": "youtube#video", "etag": "\"j6xRRd8dTPVVptg711_CSPADRfg/4C1_rBXJPYJaUeR4C77os2wsgjs\"", "id": "hyvKnvLccvA", "contentDetails": {"duration": "PT23M11S", "dimension": "2d", "definition": "hd", "caption": "false", "licensedContent": true, "projection": "rectangular"}}, {"kind": "youtube#video", "etag": "\"j6xRRd8dTPVVptg711_CSPADRfg/Caf-Bqqn1wcnPpE_y8zjJq2ECBc\"", "id": "p80Ltsq8l9o", "contentDetails": {"duration": "PT1M29S", "dimension": "2d", "definition": "hd", "caption": "false", "licensedContent": false, "contentRating": {"ytRating": "ytAgeRestricted"}, "projection": "rectangular"}}, {"kind": "youtube#video", "etag": "\"j6xRRd8dTPVVptg711_CSPADRfg/-JIsgSg-RX-S7vs_VFevOTTYCFk\"", "id": "-ti9djgwNcw", "contentDetails": {"duration": "PT1M54S", "dimension": "2d", "definition": "hd", "caption": "false", "licensedContent": false, "projection": "rectangular"}}, {"kind": "youtube#video", "etag": "\"j6xRRd8dTPVVptg711_CSPADRfg/UeevgWjnkId0kVwFc8ZBA4KrlhE\"", "id": "mBrdEYW0Vno", "contentDetails": {"duration": "PT4M3S", "dimension": "2d", "definition": "hd", "caption": "false", "licensedContent": true, "projection": "rectangular"}}, {"kind": "youtube#video", "etag": "\"j6xRRd8dTPVVptg711_CSPADRfg/6psKHsDX_yc2tYb8akLKnVHLGiQ\"", "id": "hYC0XFHiqJs", "contentDetails": {"duration": "PT1M", "dimension": "2d", "definition": "sd", "caption": "false", "licensedContent": true, "projection": "rectangular"}}, {"kind": "youtube#video", "etag": "\"j6xRRd8dTPVVptg711_CSPADRfg/1c_Km8LzSYid3YzrsGI7JtjO9nM\"", "id": "pwrq-c1EVAs", "contentDetails": {"duration": "PT9M18S", "dimension": "2d", "definition": "hd", "caption": "false", "licensedContent": true, "projection": "rectangular"}}]}