{"kind": "youtube#videoListResponse", "etag": "\"j6xRRd8dTPVVptg711_CSPADRfg/oW9dbH5ybxQseK7s0iE28VBNgbM\"", "pageInfo": {"totalResults": 28, "resultsPerPage": 28}, "items": [{"kind": "youtube#video", "etag": "\"j6xRRd8dTPVVptg711_CSPADRfg/QAMrQhEgRQjiErSnma-rRIeguW8\"", "id": "2J2H8vP2y-0", "contentDetails": {"duration": "PT6M12S", "dimension": "2d", "definition": "hd", "caption": "false", "licensedContent": true, "projection": "rectangular"}}, {"kind": "youtube#video", "etag": "\"j6xRRd8dTPVVptg711_CSPADRfg/SKJuvDi6FVR9XiVJxescASbj3cM\"", "id": "Svsgr2OHhpk", "contentDetails": {"duration": "PT6M41S", "dimension": "2d", "definition": "hd", "caption": "false", "licensedContent": false, "projection": "rectangular"}}, {"kind": "youtube#video", "etag": "\"j6xRRd8dTPVVptg711_CSPADRfg/OGgDoqxYhOZXBA5nrkPQmcQIUqs\"", "id": "CYLWkh9UowI", "contentDetails": {"duration": "PT5M3S", "dimension": "2d", "definition": "hd", "caption": "false", "licensedContent": true, "projection": "rectangular"}}, {"kind": "youtube#video", "etag": "\"j6xRRd8dTPVVptg711_CSPADRfg/Zou48pETCcTCYnZXpbZQTXIPPSI\"", "id": "dhHJ_AqOs28", "contentDetails": {"duration": "PT11M21S", "dimension": "2d", "definition": "hd", "caption": "false", "licensedContent": true, "projection": "rectangular"}}, {"kind": "youtube#video", "etag": "\"j6xRRd8dTPVVptg711_CSPADRfg/eNYdKa48-8PdoCkf-nDOIZniBoI\"", "id": "UdWH-skptQY", "contentDetails": {"duration": "PT12M17S", "dimension": "2d", "definition": "hd", "caption": "false", "licensedContent": true, "projection": "rectangular"}}, {"kind": "youtube#video", "etag": "\"j6xRRd8dTPVVptg711_CSPADRfg/gQpXfwYyMyjK7x5jGKWZQ4uLc4E\"", "id": "XDv_9U7RDZQ", "contentDetails": {"duration": "PT40M31S", "dimension": "2d", "definition": "hd", "caption": "true", "licensedContent": true, "projection": "rectangular"}}, {"kind": "youtube#video", "etag": "\"j6xRRd8dTPVVptg711_CSPADRfg/vDE_D_pnBXm6h0V3F1bCYv1wAwM\"", "id": "7bK-DMdx-Gs", "contentDetails": {"duration": "PT9M20S", "dimension": "2d", "definition": "hd", "caption": "false", "licensedContent": false, "projection": "rectangular"}}, {"kind": "youtube#video", "etag": "\"j6xRRd8dTPVVptg711_CSPADRfg/khXLpSkC6nZ-pO2fJjFtH6-A8EA\"", "id": "jbKMGQDCLX4", "contentDetails": {"duration": "PT5M28S", "dimension": "2d", "definition": "hd", "caption": "false", "licensedContent": true, "projection": "rectangular"}}, {"kind": "youtube#video", "etag": "\"j6xRRd8dTPVVptg711_CSPADRfg/i2K7OBjORkcyVCF41Yt2RiqFJy8\"", "id": "M0Pwtd5aG30", "contentDetails": {"duration": "PT5M11S", "dimension": "2d", "definition": "hd", "caption": "false", "licensedContent": true, "projection": "rectangular"}}, {"kind": "youtube#video", "etag": "\"j6xRRd8dTPVVptg711_CSPADRfg/60bj_vSYhYxs4xiOhuwizoqaYZM\"", "id": "GlJo3Z5C4SE", "contentDetails": {"duration": "PT13M7S", "dimension": "2d", "definition": "hd", "caption": "false", "licensedContent": true, "projection": "rectangular"}}, {"kind": "youtube#video", "etag": "\"j6xRRd8dTPVVptg711_CSPADRfg/DlSvH4rzOIBqi9cuq0DyVWbRKi8\"", "id": "g3OexFWv8Os", "contentDetails": {"duration": "PT35M51S", "dimension": "2d", "definition": "hd", "caption": "true", "licensedContent": true, "projection": "rectangular"}}, {"kind": "youtube#video", "etag": "\"j6xRRd8dTPVVptg711_CSPADRfg/7rusqM9JkEjlJmLAlUdWwSuxDS8\"", "id": "QayAI61sVBY", "contentDetails": {"duration": "PT6M17S", "dimension": "2d", "definition": "hd", "caption": "true", "licensedContent": true, "projection": "rectangular"}}, {"kind": "youtube#video", "etag": "\"j6xRRd8dTPVVptg711_CSPADRfg/SG_M6JVBYlO0t3HW1LIwfXasLI4\"", "id": "nxX5PrTa3O0", "contentDetails": {"duration": "PT3M56S", "dimension": "2d", "definition": "hd", "caption": "true", "licensedContent": true, "projection": "rectangular"}}, {"kind": "youtube#video", "etag": "\"j6xRRd8dTPVVptg711_CSPADRfg/e4jh9AvZwVW4ig_XmgQzkwLUbmA\"", "id": "tHmNuMMdKqU", "contentDetails": {"duration": "PT21M", "dimension": "2d", "definition": "hd", "caption": "false", "licensedContent": true, "projection": "rectangular"}}, {"kind": "youtube#video", "etag": "\"j6xRRd8dTPVVptg711_CSPADRfg/RpERTvhJI62vZiH_WXDGkxp8oks\"", "id": "mSAPgDuf5xg", "contentDetails": {"duration": "PT14M56S", "dimension": "2d", "definition": "hd", "caption": "false", "licensedContent": true, "projection": "rectangular"}}, {"kind": "youtube#video", "etag": "\"j6xRRd8dTPVVptg711_CSPADRfg/vVJBsUZfeV5PYl9H4TDL3zJBQ4E\"", "id": "n9cvWeYjJ8E", "contentDetails": {"duration": "PT1H19M39S", "dimension": "2d", "definition": "hd", "caption": "false", "licensedContent": false, "projection": "rectangular"}}, {"kind": "youtube#video", "etag": "\"j6xRRd8dTPVVptg711_CSPADRfg/mOkkgTwNQ2KkRdClUAJHS6dQhd4\"", "id": "K-XrEvbigDM", "contentDetails": {"duration": "PT6M56S", "dimension": "2d", "definition": "hd", "caption": "true", "licensedContent": true, "regionRestriction": {"allowed": ["RW", "GN", "NE", "LB", "NC", "PM", "HT", "RE", "PF", "LU", "YT", "BF", "BE", "BJ", "BI", "DZ", "BL", "DJ", "DM", "DO", "ML", "MC", "MA", "MF", "MG", "MD", "MZ", "SC", "MR", "SN", "MQ", "WF", "FR", "CD", "CF", "CG", "CA", "TG", "TF", "CM", "MU", "GA", "CH", "CI", "GF", "TN", "KM", "TD", "GP", "GQ", "AD", "GW"]}, "projection": "rectangular"}}, {"kind": "youtube#video", "etag": "\"j6xRRd8dTPVVptg711_CSPADRfg/WZiM8wZUjcVVg-w5NqyLWO8WZv0\"", "id": "lh45Wgy3nmA", "contentDetails": {"duration": "PT1M33S", "dimension": "2d", "definition": "hd", "caption": "false", "licensedContent": true, "projection": "rectangular"}}, {"kind": "youtube#video", "etag": "\"j6xRRd8dTPVVptg711_CSPADRfg/aQDZS6cjPk2mSRhI--cLX5S60zk\"", "id": "d-1dgQw0N2k", "contentDetails": {"duration": "PT11M52S", "dimension": "2d", "definition": "hd", "caption": "false", "licensedContent": true, "projection": "rectangular"}}, {"kind": "youtube#video", "etag": "\"j6xRRd8dTPVVptg711_CSPADRfg/29yr8JbUH7BYJV_IHn9G6INu2HE\"", "id": "dunNND_NtMg", "contentDetails": {"duration": "PT23M38S", "dimension": "2d", "definition": "hd", "caption": "false", "licensedContent": true, "projection": "rectangular"}}, {"kind": "youtube#video", "etag": "\"j6xRRd8dTPVVptg711_CSPADRfg/QA64ndVoL_lCJFXiURWmIvcsL5Y\"", "id": "8Oc6UyZu6SA", "contentDetails": {"duration": "PT16S", "dimension": "2d", "definition": "hd", "caption": "false", "licensedContent": false, "projection": "rectangular"}}, {"kind": "youtube#video", "etag": "\"j6xRRd8dTPVVptg711_CSPADRfg/pPsRHxL_rs9d_XyIFh9W5IJUm_Y\"", "id": "VeHtqSl_gyQ", "contentDetails": {"duration": "PT20M55S", "dimension": "2d", "definition": "hd", "caption": "true", "licensedContent": true, "projection": "rectangular"}}, {"kind": "youtube#video", "etag": "\"j6xRRd8dTPVVptg711_CSPADRfg/tLTgQHxU9UFmvRcNpkC8j9LJX3o\"", "id": "WMsXzFR5kn0", "contentDetails": {"duration": "PT1M22S", "dimension": "2d", "definition": "hd", "caption": "false", "licensedContent": true, "projection": "rectangular"}}, {"kind": "youtube#video", "etag": "\"j6xRRd8dTPVVptg711_CSPADRfg/0v9jG5-enclD0sCsRLc5DICxpQM\"", "id": "mQH36pFI7aw", "contentDetails": {"duration": "PT9M30S", "dimension": "2d", "definition": "hd", "caption": "true", "licensedContent": false, "projection": "rectangular"}}, {"kind": "youtube#video", "etag": "\"j6xRRd8dTPVVptg711_CSPADRfg/HG2K6ythVjL3kKUH70mEuMgKwDk\"", "id": "MfFcvg1BBKc", "contentDetails": {"duration": "PT6M10S", "dimension": "2d", "definition": "hd", "caption": "false", "licensedContent": true, "projection": "rectangular"}}, {"kind": "youtube#video", "etag": "\"j6xRRd8dTPVVptg711_CSPADRfg/COnCKWNTi9Lib-AgFKFGcw-1LZ0\"", "id": "WKseS4JrihI", "contentDetails": {"duration": "PT9M36S", "dimension": "2d", "definition": "hd", "caption": "false", "licensedContent": true, "projection": "rectangular"}}, {"kind": "youtube#video", "etag": "\"j6xRRd8dTPVVptg711_CSPADRfg/2Tk6zf52p-7CrJLls58VIH-hvM4\"", "id": "ctJTlOjtWac", "contentDetails": {"duration": "PT10M34S", "dimension": "2d", "definition": "hd", "caption": "false", "licensedContent": true, "projection": "rectangular"}}, {"kind": "youtube#video", "etag": "\"j6xRRd8dTPVVptg711_CSPADRfg/17eDgcPRju7-zv0TIQR6p7TSINU\"", "id": "tqdY01Zzvn0", "contentDetails": {"duration": "PT4M24S", "dimension": "2d", "definition": "hd", "caption": "false", "licensedContent": false, "projection": "rectangular"}}]}