{"kind": "youtube#videoListResponse", "etag": "\"j6xRRd8dTPVVptg711_CSPADRfg/POnK5R24IPlOcBD9_g1y8McS6qk\"", "pageInfo": {"totalResults": 30, "resultsPerPage": 30}, "items": [{"kind": "youtube#video", "etag": "\"j6xRRd8dTPVVptg711_CSPADRfg/-MQtGRAQWBSqD_XnZov5QFNIIIY\"", "id": "4y8-Xxo53pM", "contentDetails": {"duration": "PT4M12S", "dimension": "2d", "definition": "sd", "caption": "false", "licensedContent": true, "projection": "rectangular"}}, {"kind": "youtube#video", "etag": "\"j6xRRd8dTPVVptg711_CSPADRfg/jlV3zEtERo0JQKc_GyhsFaO9JPs\"", "id": "BDJRxNkzjQc", "contentDetails": {"duration": "PT8M4S", "dimension": "2d", "definition": "hd", "caption": "true", "licensedContent": true, "projection": "rectangular"}}, {"kind": "youtube#video", "etag": "\"j6xRRd8dTPVVptg711_CSPADRfg/cDI4dmPDumj_BcMKMTJjUriSPpM\"", "id": "gJDrXGZ_cf4", "contentDetails": {"duration": "PT45S", "dimension": "2d", "definition": "sd", "caption": "false", "licensedContent": true, "projection": "rectangular"}}, {"kind": "youtube#video", "etag": "\"j6xRRd8dTPVVptg711_CSPADRfg/6-L69FQKLEZp6YUURWjj9URzfq8\"", "id": "dfnCAmr569k", "contentDetails": {"duration": "PT4M11S", "dimension": "2d", "definition": "hd", "caption": "true", "licensedContent": true, "projection": "rectangular"}}, {"kind": "youtube#video", "etag": "\"j6xRRd8dTPVVptg711_CSPADRfg/KJK4RNUVSMHx7OPaUjEkDXy2Xd0\"", "id": "muGwQEScRb8", "contentDetails": {"duration": "PT3M4S", "dimension": "2d", "definition": "hd", "caption": "false", "licensedContent": true, "regionRestriction": {"blocked": ["PR", "CA", "US"]}, "projection": "rectangular"}}, {"kind": "youtube#video", "etag": "\"j6xRRd8dTPVVptg711_CSPADRfg/BPKa37EMvSl6QySSdiptIKcjCio\"", "id": "RmJaVQo_afA", "contentDetails": {"duration": "PT47M35S", "dimension": "2d", "definition": "hd", "caption": "false", "licensedContent": true, "projection": "rectangular"}}, {"kind": "youtube#video", "etag": "\"j6xRRd8dTPVVptg711_CSPADRfg/5dV9JNAmc2iVCBvxiwjLL3p6ZDQ\"", "id": "5CAEK6Yd-Y0", "contentDetails": {"duration": "PT7M36S", "dimension": "2d", "definition": "hd", "caption": "true", "licensedContent": true, "projection": "rectangular"}}, {"kind": "youtube#video", "etag": "\"j6xRRd8dTPVVptg711_CSPADRfg/1VViv7qwsEefE83SVKgbYkP3zv0\"", "id": "u34X8ao4znc", "contentDetails": {"duration": "PT9M21S", "dimension": "2d", "definition": "hd", "caption": "false", "licensedContent": true, "projection": "rectangular"}}, {"kind": "youtube#video", "etag": "\"j6xRRd8dTPVVptg711_CSPADRfg/8DdZxgsPYWvhRK_P9CNNNZhGShM\"", "id": "Mgfe5tIwOj0", "contentDetails": {"duration": "PT3M51S", "dimension": "2d", "definition": "hd", "caption": "false", "licensedContent": true, "projection": "rectangular"}}, {"kind": "youtube#video", "etag": "\"j6xRRd8dTPVVptg711_CSPADRfg/t70iOZQ1V9m25AS7VTnaSqH3qPY\"", "id": "LLxsgH88Uhc", "contentDetails": {"duration": "PT3M39S", "dimension": "2d", "definition": "hd", "caption": "false", "licensedContent": true, "projection": "rectangular"}}, {"kind": "youtube#video", "etag": "\"j6xRRd8dTPVVptg711_CSPADRfg/pOM0BWUYQKSaRePBEXaEDBgANIQ\"", "id": "rRuwrwZZXvY", "contentDetails": {"duration": "PT5M56S", "dimension": "2d", "definition": "hd", "caption": "false", "licensedContent": true, "projection": "rectangular"}}, {"kind": "youtube#video", "etag": "\"j6xRRd8dTPVVptg711_CSPADRfg/v81bGTVbxuHWWi7ltmTZnIG9TLo\"", "id": "t5MIlVmv7EM", "contentDetails": {"duration": "PT1M37S", "dimension": "2d", "definition": "hd", "caption": "true", "licensedContent": true, "projection": "rectangular"}}, {"kind": "youtube#video", "etag": "\"j6xRRd8dTPVVptg711_CSPADRfg/UiFadqSigDrmEYQTmIyrXEUU5vg\"", "id": "GH2Qn4hvCI0", "contentDetails": {"duration": "PT38M19S", "dimension": "2d", "definition": "hd", "caption": "true", "licensedContent": true, "projection": "rectangular"}}, {"kind": "youtube#video", "etag": "\"j6xRRd8dTPVVptg711_CSPADRfg/dmC9kO-UZf-8SIryqSS_Q3IDuGQ\"", "id": "PH3JVEjinnE", "contentDetails": {"duration": "PT12M16S", "dimension": "2d", "definition": "hd", "caption": "false", "licensedContent": false, "projection": "rectangular"}}, {"kind": "youtube#video", "etag": "\"j6xRRd8dTPVVptg711_CSPADRfg/lprMvYq153TJAsg9byK3CNOw0BU\"", "id": "vpblg9J3vKE", "contentDetails": {"duration": "PT2M42S", "dimension": "2d", "definition": "hd", "caption": "false", "licensedContent": true, "projection": "rectangular"}}, {"kind": "youtube#video", "etag": "\"j6xRRd8dTPVVptg711_CSPADRfg/HzHGLwjTkn7QgfaqL9SPWnqusdw\"", "id": "SXQfDF8doKw", "contentDetails": {"duration": "PT6M3S", "dimension": "2d", "definition": "hd", "caption": "false", "licensedContent": false, "projection": "rectangular"}}, {"kind": "youtube#video", "etag": "\"j6xRRd8dTPVVptg711_CSPADRfg/ECsvg6NEPR45t9xZIvE-q7_OMes\"", "id": "xJKHdOgA-e8", "contentDetails": {"duration": "PT29M48S", "dimension": "2d", "definition": "hd", "caption": "false", "licensedContent": true, "projection": "rectangular"}}, {"kind": "youtube#video", "etag": "\"j6xRRd8dTPVVptg711_CSPADRfg/gmmpAQEu6XpgE-1XGLbRCeJDWkY\"", "id": "xYh3dUuUoSI", "contentDetails": {"duration": "PT3M59S", "dimension": "2d", "definition": "hd", "caption": "true", "licensedContent": true, "projection": "rectangular"}}, {"kind": "youtube#video", "etag": "\"j6xRRd8dTPVVptg711_CSPADRfg/f74EKT9QqaAfDb1o2m-taw7WJq8\"", "id": "INMFy5Txtyc", "contentDetails": {"duration": "PT9M25S", "dimension": "2d", "definition": "hd", "caption": "true", "licensedContent": true, "projection": "rectangular"}}, {"kind": "youtube#video", "etag": "\"j6xRRd8dTPVVptg711_CSPADRfg/U37TAE95jDxAqoonqp7yMrNOsAE\"", "id": "MsCOyeYusJ8", "contentDetails": {"duration": "PT6M6S", "dimension": "2d", "definition": "sd", "caption": "false", "licensedContent": true, "regionRestriction": {"allowed": ["TF", "BE", "NC", "PM", "BL", "MA", "CH", "PF", "MC", "RE", "MF", "LU", "MQ", "FR", "DZ", "GP", "TN", "YT", "WF", "GF"]}, "projection": "rectangular"}}, {"kind": "youtube#video", "etag": "\"j6xRRd8dTPVVptg711_CSPADRfg/7GM4NgNQ0LvYiQC-wqT6YraW6SM\"", "id": "skrCCirPQo0", "contentDetails": {"duration": "PT3M2S", "dimension": "2d", "definition": "hd", "caption": "false", "licensedContent": true, "regionRestriction": {"allowed": ["HR", "LK", "LI", "WF", "LB", "LC", "LA", "MU", "LY", "LV", "LT", "LU", "LR", "LS", "BR", "IM", "HU", "DZ", "MP", "DE", "MS", "DO", "DM", "DJ", "DK", "TF", "TG", "IS", "IR", "IT", "TN", "TO", "TL", "TM", "TJ", "TK", "TH", "TV", "TW", "TT", "IE", "ID", "TZ", "IL", "IO", "IN", "AX", "AZ", "YE", "PL", "AQ", "AS", "AR", "AU", "AT", "AW", "AI", "AM", "YT", "AO", "AE", "AD", "AG", "AF", "NI", "NL", "NO", "QA", "NA", "NC", "CA", "NF", "NG", "NZ", "HK", "NP", "NR", "NU", "CF", "FR", "CH", "WS", "CD", "KR", "FI", "FJ", "FK", "FM", "MT", "FO", "CC", "VA", "KY", "VC", "CG", "VE", "VG", "CK", "VI", "CI", "KP", "CO", "CN", "CM", "CL", "CR", "KI", "KH", "CW", "VU", "CU", "CZ", "CY", "CX", "KG", "KE", "HN", "CV", "SS", "SR", "SV", "HT", "ST", "SZ", "SY", "SX", "BF", "SC", "SB", "SA", "SG", "SE", "SD", "SK", "SJ", "SI", "SH", "SO", "SN", "SM", "HM", "SL", "TC", "GB", "BL", "MM", "ML", "PH", "MN", "PN", "MH", "KZ", "PM", "ME", "BH", "MG", "MF", "MA", "PG", "MC", "PE", "PY", "MY", "MX", "MZ", "PR", "PS", "MW", "MV", "MQ", "PW", "PT", "MR", "ET", "KN", "ES", "ER", "EE", "EG", "BW", "EC", "EH", "KM", "IQ", "UG", "BG", "UA", "BA", "BB", "PK", "UM", "BM", "BN", "BO", "JP", "MO", "BJ", "BT", "JM", "BV", "JO", "BQ", "US", "BS", "JE", "UY", "BY", "BZ", "UZ", "ZM", "MK", "PA", "TD", "ZA", "BE", "NE", "MD", "KW", "ZW", "BD", "RU", "RW", "RS", "PF", "RE", "GF", "OM", "RO", "GY", "GW", "GU", "GT", "GS", "GR", "GQ", "GP", "GN", "GM", "GL", "GI", "GH", "GG", "TR", "GE", "GD", "VN", "BI", "GA", "AL"]}, "projection": "rectangular"}}, {"kind": "youtube#video", "etag": "\"j6xRRd8dTPVVptg711_CSPADRfg/sgr-l1Teddwc5yBHb79ZPrr39jQ\"", "id": "Jcghl0lbDSk", "contentDetails": {"duration": "PT18S", "dimension": "2d", "definition": "sd", "caption": "false", "licensedContent": false, "projection": "rectangular"}}, {"kind": "youtube#video", "etag": "\"j6xRRd8dTPVVptg711_CSPADRfg/ZmLATklbrPggr44TODZdrJliZdE\"", "id": "EIue2W8V0FQ", "contentDetails": {"duration": "PT13M47S", "dimension": "2d", "definition": "hd", "caption": "false", "licensedContent": true, "projection": "rectangular"}}, {"kind": "youtube#video", "etag": "\"j6xRRd8dTPVVptg711_CSPADRfg/KHL3x_T2bHXauFMiG0PD3AsfUD0\"", "id": "5IqFcfQq-9I", "contentDetails": {"duration": "PT9M10S", "dimension": "2d", "definition": "hd", "caption": "false", "licensedContent": true, "projection": "rectangular"}}, {"kind": "youtube#video", "etag": "\"j6xRRd8dTPVVptg711_CSPADRfg/oClj_XknlXtHWwcH0Yw-zMRCpHY\"", "id": "I8iN-0K5-q0", "contentDetails": {"duration": "PT11M33S", "dimension": "2d", "definition": "hd", "caption": "false", "licensedContent": true, "projection": "rectangular"}}, {"kind": "youtube#video", "etag": "\"j6xRRd8dTPVVptg711_CSPADRfg/Rh277CN2Ah6yWkopMBl3jjh_ob8\"", "id": "rXcK0yNwEg0", "contentDetails": {"duration": "PT44M30S", "dimension": "2d", "definition": "hd", "caption": "false", "licensedContent": true, "projection": "rectangular"}}, {"kind": "youtube#video", "etag": "\"j6xRRd8dTPVVptg711_CSPADRfg/v41wAzChZxAsLkbtJib0nwlLqIw\"", "id": "ZX7wTMoLQNQ", "contentDetails": {"duration": "PT15M27S", "dimension": "2d", "definition": "hd", "caption": "false", "licensedContent": true, "projection": "rectangular"}}, {"kind": "youtube#video", "etag": "\"j6xRRd8dTPVVptg711_CSPADRfg/x49_kPsszJZOsWFlqdT_7H9_6xI\"", "id": "DDSS7Yo1amw", "contentDetails": {"duration": "PT4M10S", "dimension": "2d", "definition": "hd", "caption": "false", "licensedContent": true, "projection": "rectangular"}}, {"kind": "youtube#video", "etag": "\"j6xRRd8dTPVVptg711_CSPADRfg/S43vbMOHBFDrvYdi0XXg25FRsMM\"", "id": "RkvczNWh9ZM", "contentDetails": {"duration": "PT10M5S", "dimension": "2d", "definition": "hd", "caption": "true", "licensedContent": true, "projection": "rectangular"}}, {"kind": "youtube#video", "etag": "\"j6xRRd8dTPVVptg711_CSPADRfg/cR0iwujA_P4-uLtp8JR4OwjDrnU\"", "id": "gu9_m0vm7fM", "contentDetails": {"duration": "PT4M13S", "dimension": "2d", "definition": "hd", "caption": "false", "licensedContent": true, "regionRestriction": {"allowed": ["HR", "LK", "LI", "WF", "LB", "LC", "LA", "MU", "LY", "LV", "LT", "LU", "LR", "LS", "BR", "IM", "HU", "DZ", "MP", "DE", "MS", "DO", "DM", "DJ", "DK", "TF", "TG", "IS", "IR", "IT", "TN", "TO", "TL", "TM", "TJ", "TK", "TH", "TV", "TW", "TT", "IE", "ID", "TZ", "IL", "IO", "IN", "AX", "AZ", "YE", "PL", "AQ", "AS", "AR", "AU", "AT", "AW", "AI", "AM", "YT", "AO", "AE", "AD", "AG", "AF", "NI", "NL", "NO", "QA", "NA", "NC", "CA", "NF", "NG", "NZ", "HK", "NP", "NR", "NU", "CF", "FR", "CH", "WS", "CD", "KR", "FI", "FJ", "FK", "FM", "MT", "FO", "CC", "VA", "KY", "VC", "CG", "VE", "VG", "CK", "VI", "CI", "KP", "CO", "CN", "CM", "CL", "CR", "KI", "KH", "CW", "VU", "CU", "CZ", "CY", "CX", "KG", "KE", "HN", "CV", "SS", "SR", "SV", "HT", "ST", "SZ", "SY", "SX", "BF", "SC", "SB", "SA", "SG", "SE", "SD", "SK", "SJ", "SI", "SH", "SO", "SN", "SM", "HM", "SL", "TC", "GB", "BL", "MM", "ML", "PH", "MN", "PN", "MH", "KZ", "PM", "ME", "BH", "MG", "MF", "MA", "PG", "MC", "PE", "PY", "MY", "MX", "MZ", "PR", "PS", "MW", "MV", "MQ", "PW", "PT", "MR", "ET", "KN", "ES", "ER", "EE", "EG", "BW", "EC", "EH", "KM", "IQ", "UG", "BG", "UA", "BA", "BB", "PK", "UM", "BM", "BN", "BO", "JP", "MO", "BJ", "BT", "JM", "BV", "JO", "BQ", "US", "BS", "JE", "UY", "BY", "BZ", "UZ", "ZM", "MK", "PA", "TD", "ZA", "BE", "NE", "MD", "KW", "ZW", "BD", "RU", "RW", "RS", "PF", "RE", "GF", "OM", "RO", "GY", "GW", "GU", "GT", "GS", "GR", "GQ", "GP", "GN", "GM", "GL", "GI", "GH", "GG", "TR", "GE", "GD", "VN", "BI", "GA", "AL"]}, "projection": "rectangular"}}]}