{"kind": "youtube#videoListResponse", "etag": "\"j6xRRd8dTPVVptg711_CSPADRfg/Xgkz1NG5mylpXWgIN3sPpRYBbdo\"", "pageInfo": {"totalResults": 33, "resultsPerPage": 33}, "items": [{"kind": "youtube#video", "etag": "\"j6xRRd8dTPVVptg711_CSPADRfg/JSVohcP4LKE-0R5Oqv7s_s6kdP0\"", "id": "9rOqSSRqliM", "contentDetails": {"duration": "PT12M45S", "dimension": "2d", "definition": "hd", "caption": "false", "licensedContent": true, "projection": "rectangular"}}, {"kind": "youtube#video", "etag": "\"j6xRRd8dTPVVptg711_CSPADRfg/a_Gy25fd64dftksaGEbTB3AdFYU\"", "id": "ukr425xbkTI", "contentDetails": {"duration": "PT3M49S", "dimension": "2d", "definition": "hd", "caption": "false", "licensedContent": false, "projection": "rectangular"}}, {"kind": "youtube#video", "etag": "\"j6xRRd8dTPVVptg711_CSPADRfg/s-zSJk_QgM3aWdUK9c8xLL8wc4k\"", "id": "miRG9OEYaCU", "contentDetails": {"duration": "PT3M9S", "dimension": "2d", "definition": "hd", "caption": "false", "licensedContent": true, "projection": "rectangular"}}, {"kind": "youtube#video", "etag": "\"j6xRRd8dTPVVptg711_CSPADRfg/OOg9Mf6wDiFGec_VNcHtOnw4PT0\"", "id": "HiDuZyoxX6E", "contentDetails": {"duration": "PT29M31S", "dimension": "2d", "definition": "hd", "caption": "false", "licensedContent": true, "projection": "rectangular"}}, {"kind": "youtube#video", "etag": "\"j6xRRd8dTPVVptg711_CSPADRfg/JC22K6L4AW3B212s52o3zI3zZBk\"", "id": "sVJ0ig856Us", "contentDetails": {"duration": "PT9M41S", "dimension": "2d", "definition": "hd", "caption": "false", "licensedContent": true, "projection": "rectangular"}}, {"kind": "youtube#video", "etag": "\"j6xRRd8dTPVVptg711_CSPADRfg/NANPXAZIMUKbcwXGPlZE3m9sHAk\"", "id": "L75Y1UT4Tgc", "contentDetails": {"duration": "PT15M48S", "dimension": "2d", "definition": "hd", "caption": "false", "licensedContent": true, "projection": "rectangular"}}, {"kind": "youtube#video", "etag": "\"j6xRRd8dTPVVptg711_CSPADRfg/__5lZ_2PFi2RTCuPLkAWYXzgtbw\"", "id": "qP9goGCvBQ4", "contentDetails": {"duration": "PT46M17S", "dimension": "2d", "definition": "hd", "caption": "false", "licensedContent": true, "projection": "rectangular"}}, {"kind": "youtube#video", "etag": "\"j6xRRd8dTPVVptg711_CSPADRfg/4Xtcy9C_2jfFuObmJBar67RgzN8\"", "id": "g6BuQjgS5YY", "contentDetails": {"duration": "PT5M38S", "dimension": "2d", "definition": "hd", "caption": "false", "licensedContent": false, "projection": "rectangular"}}, {"kind": "youtube#video", "etag": "\"j6xRRd8dTPVVptg711_CSPADRfg/j4DsIdIL23EU5c7aOKYO7WxvVwE\"", "id": "M2zuXpo2u3M", "contentDetails": {"duration": "PT10M31S", "dimension": "2d", "definition": "hd", "caption": "false", "licensedContent": true, "projection": "rectangular"}}, {"kind": "youtube#video", "etag": "\"j6xRRd8dTPVVptg711_CSPADRfg/yeEfpLJGrfH184-5FTgX5KCjd60\"", "id": "xKHO1Do_ywM", "contentDetails": {"duration": "PT23M6S", "dimension": "2d", "definition": "hd", "caption": "false", "licensedContent": false, "projection": "rectangular"}}, {"kind": "youtube#video", "etag": "\"j6xRRd8dTPVVptg711_CSPADRfg/-Z2_ed1hkFkZvZNkYQB6J6IOIPM\"", "id": "O92pekaban8", "contentDetails": {"duration": "PT1M38S", "dimension": "2d", "definition": "hd", "caption": "false", "licensedContent": true, "projection": "rectangular"}}, {"kind": "youtube#video", "etag": "\"j6xRRd8dTPVVptg711_CSPADRfg/lksUbWiIeE-K9mulLdwnyMLUvqI\"", "id": "GhOvvSoc5sg", "contentDetails": {"duration": "PT5M46S", "dimension": "2d", "definition": "hd", "caption": "false", "licensedContent": true, "projection": "rectangular"}}, {"kind": "youtube#video", "etag": "\"j6xRRd8dTPVVptg711_CSPADRfg/uSjk2S1hi19niDLcM-Vd4qZf_AY\"", "id": "JgPLYFXy66s", "contentDetails": {"duration": "PT1M19S", "dimension": "2d", "definition": "hd", "caption": "false", "licensedContent": true, "projection": "rectangular"}}, {"kind": "youtube#video", "etag": "\"j6xRRd8dTPVVptg711_CSPADRfg/fWiSPlsuPpkNa-9VVxWnBcK3Qww\"", "id": "279eLoYFGpA", "contentDetails": {"duration": "PT2H24M27S", "dimension": "2d", "definition": "hd", "caption": "false", "licensedContent": true, "regionRestriction": {"blocked": ["TR"]}, "projection": "rectangular"}}, {"kind": "youtube#video", "etag": "\"j6xRRd8dTPVVptg711_CSPADRfg/1vaiHL8RKnkJGRO7Hiwzgg_zpkY\"", "id": "pEaEYP-dR8I", "contentDetails": {"duration": "PT44M34S", "dimension": "2d", "definition": "sd", "caption": "false", "licensedContent": true, "projection": "rectangular"}}, {"kind": "youtube#video", "etag": "\"j6xRRd8dTPVVptg711_CSPADRfg/mrs8O5Yomlgj-Q60xbgDnPg36SQ\"", "id": "bi9OR0_1Wk4", "contentDetails": {"duration": "PT22M16S", "dimension": "2d", "definition": "hd", "caption": "false", "licensedContent": true, "projection": "rectangular"}}, {"kind": "youtube#video", "etag": "\"j6xRRd8dTPVVptg711_CSPADRfg/sHZmr9ldqvSCmPQETBgLDKFsZvI\"", "id": "4bw6TI9-coM", "contentDetails": {"duration": "PT12M41S", "dimension": "2d", "definition": "hd", "caption": "false", "licensedContent": true, "projection": "rectangular"}}, {"kind": "youtube#video", "etag": "\"j6xRRd8dTPVVptg711_CSPADRfg/QkEYpT8DuZ4qKBlOkV-6-sHg0io\"", "id": "uKi3CQBMs6Y", "contentDetails": {"duration": "PT3M8S", "dimension": "2d", "definition": "sd", "caption": "false", "licensedContent": true, "projection": "rectangular"}}, {"kind": "youtube#video", "etag": "\"j6xRRd8dTPVVptg711_CSPADRfg/Dre5OtFhjbj5Wxjh3LvClG3u2ys\"", "id": "NA7muoidx7c", "contentDetails": {"duration": "PT16M45S", "dimension": "2d", "definition": "hd", "caption": "false", "licensedContent": true, "projection": "rectangular"}}, {"kind": "youtube#video", "etag": "\"j6xRRd8dTPVVptg711_CSPADRfg/St9TM9bMS1nmWFtYvQAc-hdBqLU\"", "id": "3GfSx0RUIuc", "contentDetails": {"duration": "PT3M3S", "dimension": "2d", "definition": "hd", "caption": "false", "licensedContent": true, "projection": "rectangular"}}, {"kind": "youtube#video", "etag": "\"j6xRRd8dTPVVptg711_CSPADRfg/WNlSxYdh0bEEu1XH2ADh-allhjk\"", "id": "GoSwGf5dTk0", "contentDetails": {"duration": "PT21M58S", "dimension": "2d", "definition": "hd", "caption": "false", "licensedContent": true, "projection": "rectangular"}}, {"kind": "youtube#video", "etag": "\"j6xRRd8dTPVVptg711_CSPADRfg/JvMeTmnnzMfqqi4KDQ6BOEz1GiI\"", "id": "v0xBdIyNijk", "contentDetails": {"duration": "PT3M10S", "dimension": "2d", "definition": "hd", "caption": "false", "licensedContent": true, "projection": "rectangular"}}, {"kind": "youtube#video", "etag": "\"j6xRRd8dTPVVptg711_CSPADRfg/RFIpda01wwuucLibvG3juJ5wr2I\"", "id": "Oqskv6TAkT4", "contentDetails": {"duration": "PT3M58S", "dimension": "2d", "definition": "hd", "caption": "false", "licensedContent": true, "projection": "rectangular"}}, {"kind": "youtube#video", "etag": "\"j6xRRd8dTPVVptg711_CSPADRfg/UAdHBpOc14ZXg8s7djZd7ly9Beo\"", "id": "jdg90KkMCKo", "contentDetails": {"duration": "PT14M16S", "dimension": "2d", "definition": "hd", "caption": "false", "licensedContent": true, "projection": "rectangular"}}, {"kind": "youtube#video", "etag": "\"j6xRRd8dTPVVptg711_CSPADRfg/q6OKDp08BVOsyaSC8FLXTa5U0C8\"", "id": "HdFYNZ-sVxY", "contentDetails": {"duration": "PT1M6S", "dimension": "2d", "definition": "hd", "caption": "true", "licensedContent": false, "projection": "rectangular"}}, {"kind": "youtube#video", "etag": "\"j6xRRd8dTPVVptg711_CSPADRfg/061CXMK5Daj4fJMEFuQvk1Y3q_s\"", "id": "2yMlD22XwbI", "contentDetails": {"duration": "PT18S", "dimension": "2d", "definition": "hd", "caption": "false", "licensedContent": false, "projection": "rectangular"}}, {"kind": "youtube#video", "etag": "\"j6xRRd8dTPVVptg711_CSPADRfg/cDEKFXmH7hIeqZGIlRK5olDrlRg\"", "id": "mEURXE4Vrcc", "contentDetails": {"duration": "PT3M51S", "dimension": "2d", "definition": "hd", "caption": "false", "licensedContent": true, "projection": "rectangular"}}, {"kind": "youtube#video", "etag": "\"j6xRRd8dTPVVptg711_CSPADRfg/FFq_Hhz8LZ8vx45brwBAkv-_nEE\"", "id": "w6JsZW-bud0", "contentDetails": {"duration": "PT24M5S", "dimension": "2d", "definition": "hd", "caption": "false", "licensedContent": false, "projection": "rectangular"}}, {"kind": "youtube#video", "etag": "\"j6xRRd8dTPVVptg711_CSPADRfg/xIwQn4R5nIxFdgCMLSVwQyUK9-o\"", "id": "rtDuYFUQIzQ", "contentDetails": {"duration": "PT3M34S", "dimension": "2d", "definition": "hd", "caption": "false", "licensedContent": true, "projection": "rectangular"}}, {"kind": "youtube#video", "etag": "\"j6xRRd8dTPVVptg711_CSPADRfg/qoj2RNpZquxN1ErzKChJqzSYENM\"", "id": "1agILXeOSFQ", "contentDetails": {"duration": "PT12M19S", "dimension": "2d", "definition": "hd", "caption": "false", "licensedContent": true, "projection": "rectangular"}}, {"kind": "youtube#video", "etag": "\"j6xRRd8dTPVVptg711_CSPADRfg/rCtk6BOBgH2VJKy95kxGUiMPUyE\"", "id": "ymzhTiAMeWo", "contentDetails": {"duration": "PT4M35S", "dimension": "2d", "definition": "hd", "caption": "false", "licensedContent": true, "projection": "rectangular"}}, {"kind": "youtube#video", "etag": "\"j6xRRd8dTPVVptg711_CSPADRfg/EHilszbtuJOL5NbLrOrEB4rPixo\"", "id": "ybHLBlwzDiI", "contentDetails": {"duration": "PT1H49M54S", "dimension": "2d", "definition": "hd", "caption": "false", "licensedContent": false, "projection": "rectangular"}}, {"kind": "youtube#video", "etag": "\"j6xRRd8dTPVVptg711_CSPADRfg/6FNJZMKrn9wHdGb7DMB7vfA1cjQ\"", "id": "eRmvrROr-Go", "contentDetails": {"duration": "PT22M46S", "dimension": "2d", "definition": "hd", "caption": "false", "licensedContent": false, "projection": "rectangular"}}]}