{"kind": "youtube#videoListResponse", "etag": "\"j6xRRd8dTPVVptg711_CSPADRfg/eVyaWYNF5XpTeQ5SIorXhrDbfkE\"", "pageInfo": {"totalResults": 31, "resultsPerPage": 31}, "items": [{"kind": "youtube#video", "etag": "\"j6xRRd8dTPVVptg711_CSPADRfg/B21Q0qUXCO1p6zE80qd1RDSXltI\"", "id": "SmHK8K35EBc", "contentDetails": {"duration": "PT21M43S", "dimension": "2d", "definition": "hd", "caption": "false", "licensedContent": true, "projection": "rectangular"}}, {"kind": "youtube#video", "etag": "\"j6xRRd8dTPVVptg711_CSPADRfg/7Kd9RtJX1t9FJERn_NWYFQHFPbo\"", "id": "W_vLW--zyCg", "contentDetails": {"duration": "PT19M7S", "dimension": "2d", "definition": "hd", "caption": "false", "licensedContent": false, "projection": "rectangular"}}, {"kind": "youtube#video", "etag": "\"j6xRRd8dTPVVptg711_CSPADRfg/zl3xKn0KW1Ks2wle-TO9WKS4FkA\"", "id": "v-pc7rxC2XM", "contentDetails": {"duration": "PT1M43S", "dimension": "2d", "definition": "hd", "caption": "false", "licensedContent": true, "projection": "rectangular"}}, {"kind": "youtube#video", "etag": "\"j6xRRd8dTPVVptg711_CSPADRfg/TdAL2dYX7Q3LIw5a2LDFntM0kZU\"", "id": "gZ2Go5s3Pks", "contentDetails": {"duration": "PT47M25S", "dimension": "2d", "definition": "hd", "caption": "false", "licensedContent": true, "projection": "rectangular"}}, {"kind": "youtube#video", "etag": "\"j6xRRd8dTPVVptg711_CSPADRfg/I-gyinQS16NsS_2mlsyXbj8OgbQ\"", "id": "dwMmoDadFEs", "contentDetails": {"duration": "PT2M42S", "dimension": "2d", "definition": "hd", "caption": "false", "licensedContent": false, "projection": "rectangular"}}, {"kind": "youtube#video", "etag": "\"j6xRRd8dTPVVptg711_CSPADRfg/H5GF_HS2YykA7o4EvMuRZG1zVZU\"", "id": "hlwonvk2cS0", "contentDetails": {"duration": "PT10M5S", "dimension": "2d", "definition": "hd", "caption": "false", "licensedContent": true, "projection": "rectangular"}}, {"kind": "youtube#video", "etag": "\"j6xRRd8dTPVVptg711_CSPADRfg/DCICMS5kJuGL6lQZ9o4TmOhoPsQ\"", "id": "zHwEb-NDNUo", "contentDetails": {"duration": "PT21M44S", "dimension": "2d", "definition": "sd", "caption": "false", "licensedContent": true, "projection": "rectangular"}}, {"kind": "youtube#video", "etag": "\"j6xRRd8dTPVVptg711_CSPADRfg/tQ1GciXCtaHnYQxy9tiHFHjfYRo\"", "id": "kxBp1fn-uZI", "contentDetails": {"duration": "PT17M14S", "dimension": "2d", "definition": "hd", "caption": "false", "licensedContent": true, "projection": "rectangular"}}, {"kind": "youtube#video", "etag": "\"j6xRRd8dTPVVptg711_CSPADRfg/Z2PDw-5PzBFw1aRdiany2_H4Nsg\"", "id": "VuLRAspcClc", "contentDetails": {"duration": "PT3M55S", "dimension": "2d", "definition": "hd", "caption": "false", "licensedContent": true, "projection": "rectangular"}}, {"kind": "youtube#video", "etag": "\"j6xRRd8dTPVVptg711_CSPADRfg/xTmxagtH7ugspKSU-2ROJ9uQXlw\"", "id": "N8wXW_vWSw8", "contentDetails": {"duration": "PT4H54M25S", "dimension": "2d", "definition": "hd", "caption": "false", "licensedContent": true, "projection": "rectangular"}}, {"kind": "youtube#video", "etag": "\"j6xRRd8dTPVVptg711_CSPADRfg/nNva1UAj1amnxoszA9QNuMS3j3w\"", "id": "2HdJk9D6lUQ", "contentDetails": {"duration": "PT41M27S", "dimension": "2d", "definition": "sd", "caption": "false", "licensedContent": false, "regionRestriction": {"blocked": ["DE", "TR"]}, "projection": "rectangular"}}, {"kind": "youtube#video", "etag": "\"j6xRRd8dTPVVptg711_CSPADRfg/DiiC_vfh0A-owJVPU1LQKtGpZQk\"", "id": "ivXEhEJypKk", "contentDetails": {"duration": "PT1M35S", "dimension": "2d", "definition": "hd", "caption": "false", "licensedContent": true, "projection": "rectangular"}}, {"kind": "youtube#video", "etag": "\"j6xRRd8dTPVVptg711_CSPADRfg/Zz1Ar-1oUmSVmfY6-MXU7-IyP6I\"", "id": "Xu8H4EuP-UI", "contentDetails": {"duration": "PT3M31S", "dimension": "2d", "definition": "hd", "caption": "false", "licensedContent": true, "projection": "rectangular"}}, {"kind": "youtube#video", "etag": "\"j6xRRd8dTPVVptg711_CSPADRfg/XyBTyoWpjMPJCzba-yk3GeikA_Y\"", "id": "YXmy8SN3-u8", "contentDetails": {"duration": "PT3M52S", "dimension": "2d", "definition": "hd", "caption": "true", "licensedContent": true, "projection": "rectangular"}}, {"kind": "youtube#video", "etag": "\"j6xRRd8dTPVVptg711_CSPADRfg/7scyi8kLlXPvTGLJ07ca0pRAzTU\"", "id": "wi0AswO93I4", "contentDetails": {"duration": "PT7M43S", "dimension": "2d", "definition": "hd", "caption": "false", "licensedContent": false, "projection": "rectangular"}}, {"kind": "youtube#video", "etag": "\"j6xRRd8dTPVVptg711_CSPADRfg/UsraOgUfJDaMFVzj7qdk1zmpOR0\"", "id": "90vtnGojDHI", "contentDetails": {"duration": "PT16M32S", "dimension": "2d", "definition": "hd", "caption": "false", "licensedContent": true, "projection": "rectangular"}}, {"kind": "youtube#video", "etag": "\"j6xRRd8dTPVVptg711_CSPADRfg/B5ifR0WmIHlv4INeBlDi0FEGBhc\"", "id": "U8DjlWPuC0k", "contentDetails": {"duration": "PT3M40S", "dimension": "2d", "definition": "hd", "caption": "false", "licensedContent": false, "projection": "rectangular"}}, {"kind": "youtube#video", "etag": "\"j6xRRd8dTPVVptg711_CSPADRfg/q1BNuxt8lyqiw7acpIYNGrmxVkA\"", "id": "cy-Uz5PLc9s", "contentDetails": {"duration": "PT2H49M25S", "dimension": "2d", "definition": "hd", "caption": "false", "licensedContent": true, "projection": "rectangular"}}, {"kind": "youtube#video", "etag": "\"j6xRRd8dTPVVptg711_CSPADRfg/tbrthjJpSTfwl-lqcAHH7R_ytmI\"", "id": "KnoMPj9BTeU", "contentDetails": {"duration": "PT12M59S", "dimension": "2d", "definition": "hd", "caption": "false", "licensedContent": true, "projection": "rectangular"}}, {"kind": "youtube#video", "etag": "\"j6xRRd8dTPVVptg711_CSPADRfg/-CwAHnHhudWBFVQpKI1tllITXy0\"", "id": "tfNYbJggtTc", "contentDetails": {"duration": "PT8M56S", "dimension": "2d", "definition": "hd", "caption": "false", "licensedContent": true, "projection": "rectangular"}}, {"kind": "youtube#video", "etag": "\"j6xRRd8dTPVVptg711_CSPADRfg/RmDtcg_0aayMyTpNK6Dx0uGBZJE\"", "id": "ksg-OVko2qw", "contentDetails": {"duration": "PT3M56S", "dimension": "2d", "definition": "hd", "caption": "false", "licensedContent": true, "projection": "rectangular"}}, {"kind": "youtube#video", "etag": "\"j6xRRd8dTPVVptg711_CSPADRfg/v_uNotV8giuj3f1sgLk9wCc16bw\"", "id": "qZ5IHON-K2Q", "contentDetails": {"duration": "PT45M33S", "dimension": "2d", "definition": "hd", "caption": "false", "licensedContent": true, "projection": "rectangular"}}, {"kind": "youtube#video", "etag": "\"j6xRRd8dTPVVptg711_CSPADRfg/exQyNYYz_AcYuR-rHytQuLroKkw\"", "id": "YI3tQFAYATU", "contentDetails": {"duration": "PT2M18S", "dimension": "2d", "definition": "hd", "caption": "false", "licensedContent": true, "projection": "rectangular"}}, {"kind": "youtube#video", "etag": "\"j6xRRd8dTPVVptg711_CSPADRfg/n0QK3nQ4GT2Krsp1a3X9wQbgjmg\"", "id": "QA9XwUzTU78", "contentDetails": {"duration": "PT16M56S", "dimension": "2d", "definition": "hd", "caption": "false", "licensedContent": true, "projection": "rectangular"}}, {"kind": "youtube#video", "etag": "\"j6xRRd8dTPVVptg711_CSPADRfg/v9m1vbLumxMMDWCM5GNtBEqztZE\"", "id": "HnvxZEwvYjQ", "contentDetails": {"duration": "PT30M45S", "dimension": "2d", "definition": "hd", "caption": "false", "licensedContent": true, "projection": "rectangular"}}, {"kind": "youtube#video", "etag": "\"j6xRRd8dTPVVptg711_CSPADRfg/sU2bTg7Fdqu3qUwNBEgHpbfa_4I\"", "id": "XHa711ME9X8", "contentDetails": {"duration": "PT3M30S", "dimension": "2d", "definition": "hd", "caption": "false", "licensedContent": true, "projection": "rectangular"}}, {"kind": "youtube#video", "etag": "\"j6xRRd8dTPVVptg711_CSPADRfg/ymE206h9pEzzQMK-THdLuTTF5iQ\"", "id": "2-JRxHbEDRM", "contentDetails": {"duration": "PT12M43S", "dimension": "2d", "definition": "hd", "caption": "false", "licensedContent": true, "projection": "rectangular"}}, {"kind": "youtube#video", "etag": "\"j6xRRd8dTPVVptg711_CSPADRfg/yxg0iHb03KARcqNrR8Ywwd9QEgM\"", "id": "M4zrB840NsA", "contentDetails": {"duration": "PT3M2S", "dimension": "2d", "definition": "hd", "caption": "false", "licensedContent": true, "projection": "rectangular"}}, {"kind": "youtube#video", "etag": "\"j6xRRd8dTPVVptg711_CSPADRfg/rIyt_W1ewMbmyIauSNmEVxC5cew\"", "id": "7amDcsoR8ZY", "contentDetails": {"duration": "PT1H5M7S", "dimension": "2d", "definition": "hd", "caption": "false", "licensedContent": true, "projection": "rectangular"}}, {"kind": "youtube#video", "etag": "\"j6xRRd8dTPVVptg711_CSPADRfg/RjkfkzoVpZcq3DU9zkGdLVtshIs\"", "id": "KiSiucuuAGk", "contentDetails": {"duration": "PT6M8S", "dimension": "2d", "definition": "hd", "caption": "false", "licensedContent": false, "projection": "rectangular"}}, {"kind": "youtube#video", "etag": "\"j6xRRd8dTPVVptg711_CSPADRfg/ZiMgrUXoCMjWxfgYpNY03uI1P-k\"", "id": "miIE8itStfQ", "contentDetails": {"duration": "PT20M53S", "dimension": "2d", "definition": "hd", "caption": "false", "licensedContent": true, "projection": "rectangular"}}]}