{"kind": "youtube#videoListResponse", "etag": "\"j6xRRd8dTPVVptg711_CSPADRfg/BmVJNPNd8qlvdJ9Y0p2dgc9QXMc\"", "pageInfo": {"totalResults": 29, "resultsPerPage": 29}, "items": [{"kind": "youtube#video", "etag": "\"j6xRRd8dTPVVptg711_CSPADRfg/PmvJ1FOuJrgGH0eaYQUPFFH7CXU\"", "id": "KbqQFfJ_33U", "contentDetails": {"duration": "PT10M13S", "dimension": "2d", "definition": "hd", "caption": "false", "licensedContent": true, "projection": "rectangular"}}, {"kind": "youtube#video", "etag": "\"j6xRRd8dTPVVptg711_CSPADRfg/XNgtHel0VsNQBHWREDiWQq0QPNo\"", "id": "2-ORAXVRwCo", "contentDetails": {"duration": "PT11M44S", "dimension": "2d", "definition": "hd", "caption": "false", "licensedContent": true, "projection": "rectangular"}}, {"kind": "youtube#video", "etag": "\"j6xRRd8dTPVVptg711_CSPADRfg/5H4WaSY9sAmFJFxih6pfMeWgK1E\"", "id": "fRbIqg5Kz7Q", "contentDetails": {"duration": "PT1M54S", "dimension": "2d", "definition": "hd", "caption": "true", "licensedContent": true, "regionRestriction": {"allowed": ["GA", "AU", "GB", "GE", "GD", "GG", "GF", "GI", "GH", "BY", "GM", "GL", "GN", "GQ", "GP", "GS", "GR", "GU", "GT", "GW", "GY", "WS", "JE", "JO", "JM", "JP", "WF", "BN", "BO", "BL", "BM", "BJ", "BH", "BI", "BF", "BG", "BD", "BE", "BB", "BA", "HU", "BZ", "ZA", "BV", "BW", "BT", "ZM", "BR", "BS", "BQ", "MZ", "MY", "MX", "MW", "RW", "MU", "MT", "MS", "MR", "MQ", "MP", "MO", "MN", "MM", "ML", "MK", "KM", "MH", "MG", "MF", "ME", "MD", "MC", "MA", "RU", "RS", "YE", "LA", "LB", "LC", "RO", "LI", "LK", "LR", "LS", "LT", "LU", "LV", "LY", "AF", "DJ", "DK", "DM", "DO", "AD", "DE", "DZ", "AW", "AI", "TZ", "RE", "AO", "TR", "TT", "TV", "TW", "TH", "TJ", "TK", "OM", "TM", "TN", "TO", "AL", "TD", "TF", "TG", "CM", "CL", "CO", "CN", "CI", "CH", "CK", "CD", "CG", "CF", "CA", "CC", "AT", "CY", "CX", "CZ", "CU", "CW", "CV", "CR", "NZ", "SY", "SX", "SZ", "NR", "ST", "NP", "SV", "SS", "NU", "SM", "SL", "SO", "NI", "SI", "NO", "NL", "SJ", "SE", "NC", "SG", "NA", "SA", "NG", "SC", "NE", "SK", "FJ", "FK", "FI", "FO", "FM", "FR", "PG", "SD", "YT", "AS", "AR", "AQ", "VU", "IO", "IN", "IM", "IL", "NF", "AX", "IE", "ID", "VC", "VA", "AG", "VG", "AE", "VE", "IS", "IR", "IQ", "SB", "VN", "AM", "IT", "EG", "EE", "EC", "ZW", "KI", "SH", "EH", "ET", "ES", "ER", "HM", "HN", "US", "HK", "UZ", "UY", "UG", "SR", "SN", "UA", "HT", "TL", "UM", "VI", "HR", "KG", "AZ", "KR", "QA", "MV", "KE", "PE", "PF", "TC", "PA", "PL", "PM", "PN", "KN", "PH", "KH", "PK", "PT", "KW", "PW", "KP", "PR", "PS", "KY", "PY", "KZ"]}, "projection": "rectangular"}}, {"kind": "youtube#video", "etag": "\"j6xRRd8dTPVVptg711_CSPADRfg/eONGK5r5Z_0TrVdN-UFjynZYq2E\"", "id": "mUQctqVzk1M", "contentDetails": {"duration": "PT3M33S", "dimension": "2d", "definition": "hd", "caption": "false", "licensedContent": false, "projection": "rectangular"}}, {"kind": "youtube#video", "etag": "\"j6xRRd8dTPVVptg711_CSPADRfg/lVvkj9Ku_3wv4BgWRxQE36-vgyU\"", "id": "SusEf7bnR2Y", "contentDetails": {"duration": "PT1M8S", "dimension": "2d", "definition": "hd", "caption": "false", "licensedContent": true, "projection": "rectangular"}}, {"kind": "youtube#video", "etag": "\"j6xRRd8dTPVVptg711_CSPADRfg/L2iUhugfnd3wvwbPIYf2HQOHJmk\"", "id": "khPLWaBioOs", "contentDetails": {"duration": "PT2M57S", "dimension": "2d", "definition": "hd", "caption": "true", "licensedContent": true, "projection": "rectangular"}}, {"kind": "youtube#video", "etag": "\"j6xRRd8dTPVVptg711_CSPADRfg/0Ir7iD2Q6oqS6c7FzlOm7FTNnhg\"", "id": "wZfGjD5yatk", "contentDetails": {"duration": "PT7M4S", "dimension": "2d", "definition": "hd", "caption": "false", "licensedContent": false, "projection": "rectangular"}}, {"kind": "youtube#video", "etag": "\"j6xRRd8dTPVVptg711_CSPADRfg/ty--Hw3WFyKm78KZHufiEUKB30Q\"", "id": "EQK2UsS0c50", "contentDetails": {"duration": "PT48S", "dimension": "2d", "definition": "hd", "caption": "false", "licensedContent": true, "projection": "rectangular"}}, {"kind": "youtube#video", "etag": "\"j6xRRd8dTPVVptg711_CSPADRfg/3dtwSAdkXNRXB7txyProgQAivBs\"", "id": "NKvwQPvaukY", "contentDetails": {"duration": "PT4M49S", "dimension": "2d", "definition": "hd", "caption": "false", "licensedContent": true, "projection": "rectangular"}}, {"kind": "youtube#video", "etag": "\"j6xRRd8dTPVVptg711_CSPADRfg/I0mMB2Vuyd7mZx-274KWAWeIXnA\"", "id": "59-Lrvwawn4", "contentDetails": {"duration": "PT3M2S", "dimension": "2d", "definition": "hd", "caption": "false", "licensedContent": false, "projection": "rectangular"}}, {"kind": "youtube#video", "etag": "\"j6xRRd8dTPVVptg711_CSPADRfg/tLRy5Bf1FiYsbViWTtr1MV3DMl0\"", "id": "81SgHJvJWwo", "contentDetails": {"duration": "PT8M12S", "dimension": "2d", "definition": "hd", "caption": "false", "licensedContent": true, "projection": "rectangular"}}, {"kind": "youtube#video", "etag": "\"j6xRRd8dTPVVptg711_CSPADRfg/26CZ9JrNigGB5BoBPj0tzzhrBPQ\"", "id": "2CAumFG4oBE", "contentDetails": {"duration": "PT3M31S", "dimension": "2d", "definition": "hd", "caption": "false", "licensedContent": false, "projection": "rectangular"}}, {"kind": "youtube#video", "etag": "\"j6xRRd8dTPVVptg711_CSPADRfg/P5r-I-GgAdPCwIxNBiaw8o5jexo\"", "id": "Cqr1c3GLz3Q", "contentDetails": {"duration": "PT3M42S", "dimension": "2d", "definition": "hd", "caption": "false", "licensedContent": true, "regionRestriction": {"allowed": ["BL", "GF", "PM", "PF", "MQ", "FR", "GP", "WF", "MF", "RE", "MC", "TF"]}, "projection": "rectangular"}}, {"kind": "youtube#video", "etag": "\"j6xRRd8dTPVVptg711_CSPADRfg/z-MWXny8Ik3EoDV7ge2_tIuuPBo\"", "id": "ZaEjAbh2rn4", "contentDetails": {"duration": "PT6M9S", "dimension": "2d", "definition": "hd", "caption": "false", "licensedContent": true, "projection": "rectangular"}}, {"kind": "youtube#video", "etag": "\"j6xRRd8dTPVVptg711_CSPADRfg/IrZTV6Zc581hmlCetFXXqXMkc-8\"", "id": "OZIqLdd0is8", "contentDetails": {"duration": "PT11M14S", "dimension": "2d", "definition": "hd", "caption": "false", "licensedContent": true, "projection": "rectangular"}}, {"kind": "youtube#video", "etag": "\"j6xRRd8dTPVVptg711_CSPADRfg/dMuKy2Wr2WXH5cEwDMcmcWl3lP4\"", "id": "PNmr3fZiaoo", "contentDetails": {"duration": "PT6M47S", "dimension": "2d", "definition": "hd", "caption": "false", "licensedContent": true, "projection": "rectangular"}}, {"kind": "youtube#video", "etag": "\"j6xRRd8dTPVVptg711_CSPADRfg/uC2tTgeEJWYz9ctTqmPxEUzmK94\"", "id": "zngROjswfCw", "contentDetails": {"duration": "PT8M6S", "dimension": "2d", "definition": "hd", "caption": "false", "licensedContent": false, "projection": "rectangular"}}, {"kind": "youtube#video", "etag": "\"j6xRRd8dTPVVptg711_CSPADRfg/wnI2FfeWn6V9EhxuJAh8MiF4nfo\"", "id": "VP6uYuhians", "contentDetails": {"duration": "PT2H1M7S", "dimension": "2d", "definition": "hd", "caption": "false", "licensedContent": true, "projection": "rectangular"}}, {"kind": "youtube#video", "etag": "\"j6xRRd8dTPVVptg711_CSPADRfg/R4MquA-ioRQlfaG2JGKS55vRZRI\"", "id": "rOyrBPv-aQA", "contentDetails": {"duration": "PT8M56S", "dimension": "2d", "definition": "hd", "caption": "false", "licensedContent": true, "projection": "rectangular"}}, {"kind": "youtube#video", "etag": "\"j6xRRd8dTPVVptg711_CSPADRfg/zAJCwRmlQrlvTfhqe7Gaan0CKyk\"", "id": "BkgaH1Gs1lY", "contentDetails": {"duration": "PT10M16S", "dimension": "2d", "definition": "hd", "caption": "false", "licensedContent": true, "projection": "rectangular"}}, {"kind": "youtube#video", "etag": "\"j6xRRd8dTPVVptg711_CSPADRfg/gNrB4KSpyWG6-0SfeA4vEvFt13o\"", "id": "gyfG_0KiaGI", "contentDetails": {"duration": "PT10M21S", "dimension": "2d", "definition": "hd", "caption": "false", "licensedContent": true, "projection": "rectangular"}}, {"kind": "youtube#video", "etag": "\"j6xRRd8dTPVVptg711_CSPADRfg/SQdyTZo-soulchusnSoSg_dD3vY\"", "id": "GDoBJ_f5mUs", "contentDetails": {"duration": "PT2M42S", "dimension": "2d", "definition": "hd", "caption": "false", "licensedContent": false, "projection": "rectangular"}}, {"kind": "youtube#video", "etag": "\"j6xRRd8dTPVVptg711_CSPADRfg/axOEaafmKJrquCjm-5mGjWqplig\"", "id": "-SY-aeSplco", "contentDetails": {"duration": "PT4M52S", "dimension": "2d", "definition": "hd", "caption": "false", "licensedContent": true, "projection": "rectangular"}}, {"kind": "youtube#video", "etag": "\"j6xRRd8dTPVVptg711_CSPADRfg/4Y1gjglwNLzKYuwbqS4djrCxB9Y\"", "id": "yCFK-t9mb_o", "contentDetails": {"duration": "PT9M55S", "dimension": "2d", "definition": "hd", "caption": "false", "licensedContent": true, "projection": "rectangular"}}, {"kind": "youtube#video", "etag": "\"j6xRRd8dTPVVptg711_CSPADRfg/SJC9FXTgHjJVbLwGMIEiH5h2Ye4\"", "id": "CcZyr7Egi1c", "contentDetails": {"duration": "PT3M36S", "dimension": "2d", "definition": "hd", "caption": "false", "licensedContent": true, "contentRating": {"ytRating": "ytAgeRestricted"}, "projection": "rectangular"}}, {"kind": "youtube#video", "etag": "\"j6xRRd8dTPVVptg711_CSPADRfg/EDgSQDokIWjIZf6nTFSGRVaa-Q0\"", "id": "9UYqySLgRNk", "contentDetails": {"duration": "PT23M32S", "dimension": "2d", "definition": "hd", "caption": "false", "licensedContent": true, "regionRestriction": {"blocked": ["US"]}, "projection": "rectangular"}}, {"kind": "youtube#video", "etag": "\"j6xRRd8dTPVVptg711_CSPADRfg/N2WNsYV8Kyv3pNKg_tyX4l6AWbo\"", "id": "XygJJtKo0gc", "contentDetails": {"duration": "PT36M28S", "dimension": "2d", "definition": "hd", "caption": "false", "licensedContent": true, "projection": "rectangular"}}, {"kind": "youtube#video", "etag": "\"j6xRRd8dTPVVptg711_CSPADRfg/abmYzqqAtotHZQIXx7N_9mGHTSA\"", "id": "lAlN9NRxHK4", "contentDetails": {"duration": "PT34M39S", "dimension": "2d", "definition": "hd", "caption": "false", "licensedContent": true, "projection": "rectangular"}}, {"kind": "youtube#video", "etag": "\"j6xRRd8dTPVVptg711_CSPADRfg/f5k6ttxxACBDsvSV4Z2pwTFd-mA\"", "id": "wHTIs_pii8M", "contentDetails": {"duration": "PT11M43S", "dimension": "2d", "definition": "hd", "caption": "true", "licensedContent": true, "projection": "rectangular"}}]}