{"kind": "youtube#videoListResponse", "etag": "\"j6xRRd8dTPVVptg711_CSPADRfg/fQZBDYkopczFHZ02ds8wM880mcI\"", "pageInfo": {"totalResults": 33, "resultsPerPage": 33}, "items": [{"kind": "youtube#video", "etag": "\"j6xRRd8dTPVVptg711_CSPADRfg/6mikamIoYBwHcJmvNBQtEfLSCG8\"", "id": "AisWm_niafc", "contentDetails": {"duration": "PT5M8S", "dimension": "2d", "definition": "hd", "caption": "false", "licensedContent": true, "projection": "rectangular"}}, {"kind": "youtube#video", "etag": "\"j6xRRd8dTPVVptg711_CSPADRfg/WE1Q5cvFQIICvy3jwqBWUe7O2iA\"", "id": "JlV8ywB6Hbc", "contentDetails": {"duration": "PT5M26S", "dimension": "2d", "definition": "hd", "caption": "false", "licensedContent": true, "projection": "rectangular"}}, {"kind": "youtube#video", "etag": "\"j6xRRd8dTPVVptg711_CSPADRfg/IAhYvse5w0xhCfUf_GAuGG09PhE\"", "id": "FV1pMgB2pMg", "contentDetails": {"duration": "PT5M45S", "dimension": "2d", "definition": "hd", "caption": "false", "licensedContent": true, "projection": "rectangular"}}, {"kind": "youtube#video", "etag": "\"j6xRRd8dTPVVptg711_CSPADRfg/28eMzCevcYOusYnv2xjokeHUpHs\"", "id": "m6O2mgpIObY", "contentDetails": {"duration": "PT10M43S", "dimension": "2d", "definition": "hd", "caption": "true", "licensedContent": true, "projection": "rectangular"}}, {"kind": "youtube#video", "etag": "\"j6xRRd8dTPVVptg711_CSPADRfg/RGjCAiZIXDf51jR6Bipm4phdthM\"", "id": "XfAHQOZghZ4", "contentDetails": {"duration": "PT7M13S", "dimension": "2d", "definition": "hd", "caption": "true", "licensedContent": true, "projection": "rectangular"}}, {"kind": "youtube#video", "etag": "\"j6xRRd8dTPVVptg711_CSPADRfg/fEllb4x20IDTqrxqrXcGtEDAT3c\"", "id": "_DUbRm__O5I", "contentDetails": {"duration": "PT11M14S", "dimension": "2d", "definition": "hd", "caption": "false", "licensedContent": true, "projection": "rectangular"}}, {"kind": "youtube#video", "etag": "\"j6xRRd8dTPVVptg711_CSPADRfg/Gv65TVjpbLChVG_qwbqVB9qyEG8\"", "id": "D9_HxoW_CYk", "contentDetails": {"duration": "PT15M15S", "dimension": "2d", "definition": "hd", "caption": "true", "licensedContent": true, "projection": "rectangular"}}, {"kind": "youtube#video", "etag": "\"j6xRRd8dTPVVptg711_CSPADRfg/RqEqWwUmkxhTOgEfb6S27wZP2XU\"", "id": "lmpE0wNy3eQ", "contentDetails": {"duration": "PT8M32S", "dimension": "2d", "definition": "hd", "caption": "false", "licensedContent": false, "projection": "rectangular"}}, {"kind": "youtube#video", "etag": "\"j6xRRd8dTPVVptg711_CSPADRfg/B1HPAT9qoPnHL9LdKfsx617txV4\"", "id": "c8E_xjzIuOM", "contentDetails": {"duration": "PT15M44S", "dimension": "2d", "definition": "hd", "caption": "false", "licensedContent": true, "projection": "rectangular"}}, {"kind": "youtube#video", "etag": "\"j6xRRd8dTPVVptg711_CSPADRfg/Uz-I0LHxfF9mmFgj42Rq1p0oFbA\"", "id": "Sc2pkWWe4Og", "contentDetails": {"duration": "PT6M28S", "dimension": "2d", "definition": "hd", "caption": "true", "licensedContent": true, "projection": "rectangular"}}, {"kind": "youtube#video", "etag": "\"j6xRRd8dTPVVptg711_CSPADRfg/Qf-8Na4iiQj6xVeJlHMzgx_vGFM\"", "id": "oISxgk8BTYs", "contentDetails": {"duration": "PT3M25S", "dimension": "2d", "definition": "hd", "caption": "false", "licensedContent": true, "regionRestriction": {"allowed": ["MQ", "GF", "RE", "MC", "GP", "PF", "MF", "BL", "WF", "PM", "FR", "TF"]}, "projection": "rectangular"}}, {"kind": "youtube#video", "etag": "\"j6xRRd8dTPVVptg711_CSPADRfg/5vkoJaNypD4UhK2HmuYfyHv8ryM\"", "id": "sgEiSPrir6c", "contentDetails": {"duration": "PT5M48S", "dimension": "2d", "definition": "hd", "caption": "true", "licensedContent": true, "projection": "rectangular"}}, {"kind": "youtube#video", "etag": "\"j6xRRd8dTPVVptg711_CSPADRfg/wBddApUmjPYke_zt-YxbEWJUWxI\"", "id": "lMn1UstYL-I", "contentDetails": {"duration": "PT16M40S", "dimension": "2d", "definition": "hd", "caption": "true", "licensedContent": true, "projection": "rectangular"}}, {"kind": "youtube#video", "etag": "\"j6xRRd8dTPVVptg711_CSPADRfg/MfM9zi8S5vMtZwc5nAHHEEzXHqA\"", "id": "qbLgUtaR9XQ", "contentDetails": {"duration": "PT3M7S", "dimension": "2d", "definition": "hd", "caption": "false", "licensedContent": true, "projection": "rectangular"}}, {"kind": "youtube#video", "etag": "\"j6xRRd8dTPVVptg711_CSPADRfg/Oh2BdsUzPaafGt3RdS09c60R88U\"", "id": "m50utO7lnqI", "contentDetails": {"duration": "PT4M24S", "dimension": "2d", "definition": "sd", "caption": "false", "licensedContent": false, "regionRestriction": {"blocked": ["FR"]}, "projection": "rectangular"}}, {"kind": "youtube#video", "etag": "\"j6xRRd8dTPVVptg711_CSPADRfg/bH_P2msTPvSTqr77Kkn8t3qISrQ\"", "id": "ljpPtgCJ6sE", "contentDetails": {"duration": "PT13M55S", "dimension": "2d", "definition": "hd", "caption": "false", "licensedContent": false, "projection": "rectangular"}}, {"kind": "youtube#video", "etag": "\"j6xRRd8dTPVVptg711_CSPADRfg/qLvwL7KUU60Qw9usvxtJJjP3idE\"", "id": "6Bu_scosTno", "contentDetails": {"duration": "PT20M8S", "dimension": "2d", "definition": "hd", "caption": "false", "licensedContent": true, "regionRestriction": {"blocked": ["US", "CA"]}, "projection": "rectangular"}}, {"kind": "youtube#video", "etag": "\"j6xRRd8dTPVVptg711_CSPADRfg/7SuMtBraKFd0H6NbW6XZ2dBJhCM\"", "id": "auKdM1N93cY", "contentDetails": {"duration": "PT24M58S", "dimension": "2d", "definition": "hd", "caption": "false", "licensedContent": true, "projection": "rectangular"}}, {"kind": "youtube#video", "etag": "\"j6xRRd8dTPVVptg711_CSPADRfg/ccBt3SnbrL02kwjumdzarDtDd4A\"", "id": "LR8--ZDYjqo", "contentDetails": {"duration": "PT9M42S", "dimension": "2d", "definition": "hd", "caption": "false", "licensedContent": true, "projection": "rectangular"}}, {"kind": "youtube#video", "etag": "\"j6xRRd8dTPVVptg711_CSPADRfg/wwDCoxWTGj04_RVnkz9R5ZgeP3I\"", "id": "XMS4O-HsBKw", "contentDetails": {"duration": "PT2M24S", "dimension": "2d", "definition": "hd", "caption": "false", "licensedContent": true, "projection": "rectangular"}}, {"kind": "youtube#video", "etag": "\"j6xRRd8dTPVVptg711_CSPADRfg/DC3K6Exgomiy667xmcCgQGVNkbY\"", "id": "GqpZEpoNkXE", "contentDetails": {"duration": "PT4M38S", "dimension": "2d", "definition": "hd", "caption": "true", "licensedContent": true, "projection": "rectangular"}}, {"kind": "youtube#video", "etag": "\"j6xRRd8dTPVVptg711_CSPADRfg/MpaPyJ5Nz3DnPLckMPds8vcwzBk\"", "id": "d5U_RavCqLw", "contentDetails": {"duration": "PT8M3S", "dimension": "2d", "definition": "hd", "caption": "false", "licensedContent": true, "projection": "rectangular"}}, {"kind": "youtube#video", "etag": "\"j6xRRd8dTPVVptg711_CSPADRfg/z7foqaAE_sd2mmBYwa8svqLCgxg\"", "id": "7wwXthuL6vU", "contentDetails": {"duration": "PT4M25S", "dimension": "2d", "definition": "hd", "caption": "true", "licensedContent": false, "projection": "rectangular"}}, {"kind": "youtube#video", "etag": "\"j6xRRd8dTPVVptg711_CSPADRfg/L_pt6QAePZzI6mFzAsm53KJ3P2U\"", "id": "bNeua-iaTwM", "contentDetails": {"duration": "PT17M32S", "dimension": "2d", "definition": "hd", "caption": "true", "licensedContent": true, "projection": "rectangular"}}, {"kind": "youtube#video", "etag": "\"j6xRRd8dTPVVptg711_CSPADRfg/qESQUFXu0UhVvrYo8_g8Z5MH_Dk\"", "id": "BypPq2tWoj4", "contentDetails": {"duration": "PT6M39S", "dimension": "2d", "definition": "hd", "caption": "false", "licensedContent": true, "projection": "rectangular"}}, {"kind": "youtube#video", "etag": "\"j6xRRd8dTPVVptg711_CSPADRfg/Osrn8vWlqQAqFuY3dCODD3v-12Y\"", "id": "Z1knxz7bB3o", "contentDetails": {"duration": "PT3M23S", "dimension": "2d", "definition": "hd", "caption": "false", "licensedContent": true, "projection": "rectangular"}}, {"kind": "youtube#video", "etag": "\"j6xRRd8dTPVVptg711_CSPADRfg/OoziTOdqRtmx79pXlmCGLnQv5Jg\"", "id": "Gcrs5VN9Lgk", "contentDetails": {"duration": "PT4M12S", "dimension": "2d", "definition": "hd", "caption": "false", "licensedContent": true, "projection": "rectangular"}}, {"kind": "youtube#video", "etag": "\"j6xRRd8dTPVVptg711_CSPADRfg/_MSdbafMgOIn3-x3p3D1GZSIBzk\"", "id": "gysIKSuw-lc", "contentDetails": {"duration": "PT30M3S", "dimension": "2d", "definition": "hd", "caption": "false", "licensedContent": true, "projection": "rectangular"}}, {"kind": "youtube#video", "etag": "\"j6xRRd8dTPVVptg711_CSPADRfg/CMVf4lftGy53UwzMHTqFX7ZIRaM\"", "id": "KdsX7DLaR9c", "contentDetails": {"duration": "PT37M3S", "dimension": "2d", "definition": "hd", "caption": "false", "licensedContent": true, "projection": "rectangular"}}, {"kind": "youtube#video", "etag": "\"j6xRRd8dTPVVptg711_CSPADRfg/H3DsrEzFM6JcwwVDNWR90M5-fnw\"", "id": "i_eJEN5MwA0", "contentDetails": {"duration": "PT5M12S", "dimension": "2d", "definition": "hd", "caption": "false", "licensedContent": true, "projection": "rectangular"}}, {"kind": "youtube#video", "etag": "\"j6xRRd8dTPVVptg711_CSPADRfg/syqqnHLIRMKvb6yamwfo0J9qwHE\"", "id": "0dK1yBILG58", "contentDetails": {"duration": "PT7M24S", "dimension": "2d", "definition": "hd", "caption": "true", "licensedContent": false, "projection": "rectangular"}}, {"kind": "youtube#video", "etag": "\"j6xRRd8dTPVVptg711_CSPADRfg/-tdWqFVuqmjXPbaEUsLYNiLwoxs\"", "id": "F_r6iYD3U9U", "contentDetails": {"duration": "PT6M34S", "dimension": "2d", "definition": "hd", "caption": "false", "licensedContent": true, "projection": "rectangular"}}, {"kind": "youtube#video", "etag": "\"j6xRRd8dTPVVptg711_CSPADRfg/fLs7LCmMS38G1R_zQmAD7vWnlls\"", "id": "KutpVimSCQ8", "contentDetails": {"duration": "PT3M40S", "dimension": "2d", "definition": "hd", "caption": "false", "licensedContent": false, "projection": "rectangular"}}]}